donkit/llm/__init__.py
donkit/llm/claude_model.py
donkit/llm/donkit_model.py
donkit/llm/factory.py
donkit/llm/gemini_model.py
donkit/llm/llm_gate_model.py
donkit/llm/model_abstract.py
donkit/llm/openai_model.py
donkit/llm/vertex_model.py
donkit_llm-0.1.10.dist-info/METADATA
donkit_llm-0.1.10.dist-info/WHEEL
donkit_llm-0.1.10.dist-info/RECORD
