Metadata-Version: 2.3
Name: donkit-llm
Version: 0.1.10
Summary: Unified LLM model implementations for Donkit (OpenAI, Azure OpenAI, Claude, Vertex AI, Ollama)
License: MIT
Author: Donkit AI
Author-email: opensource@donkit.ai
Requires-Python: >=3.12,<3.14
Classifier: License :: OSI Approved :: MIT License
Classifier: Programming Language :: Python :: 3
Classifier: Programming Language :: Python :: 3.12
Classifier: Programming Language :: Python :: 3.13
Requires-Dist: anthropic[vertex] (>=0.42.0,<0.43.0)
Requires-Dist: donkit-ragops-api-gateway-client (>=0.1.5,<0.2.0)
Requires-Dist: google-auth (>=2.0.0,<3.0.0)
Requires-Dist: google-genai (>=1.38.0,<2.0.0)
Requires-Dist: openai (>=2.1.0,<3.0.0)
Requires-Dist: pydantic (>=2.8.0,<3.0.0)
